[{"line":1,"elements":[{"start_timestamp":"2022-05-01T15:42:04.195Z","line":4,"name":"AZair smoke test","description":"","id":"azair-smoke-test;azair-smoke-test","type":"scenario","keyword":"Scenario","steps":[{"result":{"duration":3649814100,"status":"passed"},"line":5,"name":"Browser is open","match":{"location":"stepDefinitions.SearchPageStepDefinition.browserIsOpen()"},"keyword":"Given "},{"result":{"duration":974307600,"status":"passed"},"line":6,"name":"User is on AZair search page","match":{"location":"stepDefinitions.SearchPageStepDefinition.userIsOnAZairSearchPage()"},"keyword":"And "},{"result":{"duration":368677700,"status":"passed"},"line":7,"name":"Select source airport: \"WRO\"","match":{"arguments":[{"val":"\"WRO\"","offset":23}],"location":"stepDefinitions.SearchPageStepDefinition.selectSourceAirport(java.lang.String)"},"keyword":"When "},{"result":{"duration":90467500,"status":"passed"},"line":8,"name":"Select Take Me Anywhere","match":{"location":"stepDefinitions.SearchPageStepDefinition.selectTakeMeAnywhere()"},"keyword":"And "},{"result":{"error_message":"org.openqa.selenium.TimeoutException: timeout: Timed out receiving message from renderer: 10.000\n  (Session info: chrome=100.0.4896.127)\nBuild info: version: '4.1.3', revision: '7b1ebf28ef'\nSystem info: host: 'LAPTOP-V9G33QUQ', ip: '10.5.0.2', os.name: 'Windows 10', os.arch: 'amd64', os.version: '10.0', java.version: '11.0.13'\nDriver info: org.openqa.selenium.chrome.ChromeDriver\nCommand: [ef0ba590d028214c2d0757b6f1b749a9, clickElement {id=c0c0917e-6807-40cb-9d65-58b97165f58c}]\nCapabilities {acceptInsecureCerts: false, browserName: chrome, browserVersion: 100.0.4896.127, chrome: {chromedriverVersion: 100.0.4896.60 (6a5d10861ce8..., userDataDir: C:\\Users\\micha\\AppData\\Loca...}, goog:chromeOptions: {debuggerAddress: localhost:54898}, javascriptEnabled: true, networkConnectionEnabled: false, pageLoadStrategy: normal, platform: WINDOWS, platformName: WINDOWS, proxy: Proxy(), se:cdp: ws://localhost:54898/devtoo..., se:cdpVersion: 100.0.4896.127, setWindowRect: true, strictFileInteractability: false, timeouts: {implicit: 0, pageLoad: 300000, script: 30000}, unhandledPromptBehavior: dismiss and notify, webauthn:extension:credBlob: true, webauthn:extension:largeBlob: true, webauthn:virtualAuthenticators: true}\nElement: [[ChromeDriver: chrome on WINDOWS (ef0ba590d028214c2d0757b6f1b749a9)] -> xpath: //input[@value='Search']]\nSession ID: ef0ba590d028214c2d0757b6f1b749a9\r\n\tat java.base/jdk.internal.reflect.NativeConstructorAccessorImpl.newInstance0(Native Method)\r\n\tat java.base/jdk.internal.reflect.NativeConstructorAccessorImpl.newInstance(NativeConstructorAccessorImpl.java:62)\r\n\tat java.base/jdk.internal.reflect.DelegatingConstructorAccessorImpl.newInstance(DelegatingConstructorAccessorImpl.java:45)\r\n\tat java.base/java.lang.reflect.Constructor.newInstance(Constructor.java:490)\r\n\tat org.openqa.selenium.remote.codec.w3c.W3CHttpResponseCodec.createException(W3CHttpResponseCodec.java:200)\r\n\tat org.openqa.selenium.remote.codec.w3c.W3CHttpResponseCodec.decode(W3CHttpResponseCodec.java:133)\r\n\tat org.openqa.selenium.remote.codec.w3c.W3CHttpResponseCodec.decode(W3CHttpResponseCodec.java:53)\r\n\tat org.openqa.selenium.remote.HttpCommandExecutor.execute(HttpCommandExecutor.java:184)\r\n\tat org.openqa.selenium.remote.service.DriverCommandExecutor.invokeExecute(DriverCommandExecutor.java:167)\r\n\tat org.openqa.selenium.remote.service.DriverCommandExecutor.execute(DriverCommandExecutor.java:142)\r\n\tat org.openqa.selenium.remote.RemoteWebDriver.execute(RemoteWebDriver.java:567)\r\n\tat org.openqa.selenium.remote.RemoteWebElement.execute(RemoteWebElement.java:251)\r\n\tat org.openqa.selenium.remote.RemoteWebElement.click(RemoteWebElement.java:77)\r\n\tat pageObjects.SearchPage.searchFlight(SearchPage.java:49)\r\n\tat stepDefinitions.SearchPageStepDefinition.performSearch(SearchPageStepDefinition.java:79)\r\n\tat ✽.Perform search(file:///C:/Users/micha/IdeaProjects/AZairTest/src/test/resources/features/SmokeTest.feature:9)\r\n","duration":26339177700,"status":"failed"},"line":9,"name":"Perform search","match":{"location":"stepDefinitions.SearchPageStepDefinition.performSearch()"},"keyword":"And "},{"result":{"duration":538500,"status":"skipped"},"line":10,"name":"User is navigated to result page","match":{"location":"stepDefinitions.SearchPageStepDefinition.user_is_navigated_to_result_page()"},"keyword":"Then "}],"tags":[{"name":"@SmokeTest"}]}],"name":"AZair smoke test","description":"","id":"azair-smoke-test","keyword":"Feature","uri":"file:src/test/resources/features/SmokeTest.feature","tags":[]},{"line":1,"elements":[{"start_timestamp":"2022-05-01T15:42:35.744Z","line":4,"name":"AZair OW Flight test no. 1","description":"","id":"azair-ow-flight-test-no.-1;azair-ow-flight-test-no.-1","type":"scenario","keyword":"Scenario","steps":[{"result":{"duration":1583967700,"status":"passed"},"line":5,"name":"Browser is open","match":{"location":"stepDefinitions.SearchPageStepDefinition.browserIsOpen()"},"keyword":"Given "},{"result":{"duration":866900700,"status":"passed"},"line":6,"name":"User is on AZair search page","match":{"location":"stepDefinitions.SearchPageStepDefinition.userIsOnAZairSearchPage()"},"keyword":"And "},{"result":{"duration":94901600,"status":"passed"},"line":7,"name":"Select one way ticket","match":{"location":"stepDefinitions.SearchPageStepDefinition.selectOneWayTicket()"},"keyword":"When "},{"result":{"duration":374010700,"status":"passed"},"line":8,"name":"Select source airport: \"BER\"","match":{"arguments":[{"val":"\"BER\"","offset":23}],"location":"stepDefinitions.SearchPageStepDefinition.selectSourceAirport(java.lang.String)"},"keyword":"And "},{"result":{"duration":914385500,"status":"passed"},"line":9,"name":"Select destination airport \"MAD\"","match":{"arguments":[{"val":"\"MAD\"","offset":27}],"location":"stepDefinitions.SearchPageStepDefinition.selectDestinationAirport(java.lang.String)"},"keyword":"And "},{"result":{"duration":245770600,"status":"passed"},"line":10,"name":"Select departure date \"01.06.2022\"","match":{"arguments":[{"val":"\"01.06.2022\"","offset":22}],"location":"stepDefinitions.SearchPageStepDefinition.selectDepartureDate(java.lang.String)"},"keyword":"And "},{"result":{"duration":322267300,"status":"passed"},"line":11,"name":"Select return date \"15.06.2022\"","match":{"arguments":[{"val":"\"15.06.2022\"","offset":19}],"location":"stepDefinitions.SearchPageStepDefinition.selectReturnDate(java.lang.String)"},"keyword":"And "},{"result":{"duration":3031145100,"status":"passed"},"line":12,"name":"Perform search","match":{"location":"stepDefinitions.SearchPageStepDefinition.performSearch()"},"keyword":"And "},{"result":{"duration":5010371500,"status":"passed"},"line":13,"name":"User is navigated to result page","match":{"location":"stepDefinitions.SearchPageStepDefinition.user_is_navigated_to_result_page()"},"keyword":"Then "}],"tags":[{"name":"@Test1"}]}],"name":"AZair OW Flight test no. 1","description":"","id":"azair-ow-flight-test-no.-1","keyword":"Feature","uri":"file:src/test/resources/features/Test1.feature","tags":[]},{"line":1,"elements":[{"start_timestamp":"2022-05-01T15:42:48.220Z","line":4,"name":"AZair OW Flight test no. 2","description":"","id":"azair-ow-flight-test-no.-2;azair-ow-flight-test-no.-2","type":"scenario","keyword":"Scenario","steps":[{"result":{"duration":1512336700,"status":"passed"},"line":5,"name":"Browser is open","match":{"location":"stepDefinitions.SearchPageStepDefinition.browserIsOpen()"},"keyword":"Given "},{"result":{"duration":954907600,"status":"passed"},"line":6,"name":"User is on AZair search page","match":{"location":"stepDefinitions.SearchPageStepDefinition.userIsOnAZairSearchPage()"},"keyword":"And "},{"result":{"duration":114195100,"status":"passed"},"line":7,"name":"Select one way ticket","match":{"location":"stepDefinitions.SearchPageStepDefinition.selectOneWayTicket()"},"keyword":"When "},{"result":{"duration":647670400,"status":"passed"},"line":8,"name":"Select source airport: \"BER\"","match":{"arguments":[{"val":"\"BER\"","offset":23}],"location":"stepDefinitions.SearchPageStepDefinition.selectSourceAirport(java.lang.String)"},"keyword":"And "},{"result":{"duration":551074800,"status":"passed"},"line":9,"name":"Select destination airport \"MAD\"","match":{"arguments":[{"val":"\"MAD\"","offset":27}],"location":"stepDefinitions.SearchPageStepDefinition.selectDestinationAirport(java.lang.String)"},"keyword":"And "},{"result":{"duration":192030900,"status":"passed"},"line":10,"name":"Select soonest departure date \"01.06.2022\"","match":{"arguments":[{"val":"\"01.06.2022\"","offset":30}],"location":"stepDefinitions.SearchPageStepDefinition.selectDepartureDate(java.lang.String)"},"keyword":"And "},{"result":{"duration":270533700,"status":"passed"},"line":11,"name":"Select latest departure date \"15.06.2022\"","match":{"arguments":[{"val":"\"15.06.2022\"","offset":29}],"location":"stepDefinitions.SearchPageStepDefinition.selectReturnDate(java.lang.String)"},"keyword":"And "},{"result":{"duration":119334800,"status":"passed"},"line":12,"name":"Select currency \"PLN\"","match":{"arguments":[{"val":"\"PLN\"","offset":16}],"location":"stepDefinitions.SearchPageStepDefinition.selectCurrency(java.lang.String)"},"keyword":"And "},{"result":{"duration":77675000,"status":"passed"},"line":13,"name":"Select maximum number of changes 0","match":{"arguments":[{"val":"0","offset":33}],"location":"stepDefinitions.SearchPageStepDefinition.selectMaxChanges(int)"},"keyword":"And "},{"result":{"duration":2032377700,"status":"passed"},"line":14,"name":"Perform search","match":{"location":"stepDefinitions.SearchPageStepDefinition.performSearch()"},"keyword":"And "},{"result":{"duration":5005126500,"status":"passed"},"line":15,"name":"User is navigated to result page","match":{"location":"stepDefinitions.SearchPageStepDefinition.user_is_navigated_to_result_page()"},"keyword":"Then "}],"tags":[{"name":"@Test2"}]}],"name":"AZair OW Flight test no. 2","description":"","id":"azair-ow-flight-test-no.-2","keyword":"Feature","uri":"file:src/test/resources/features/Test2.feature","tags":[]}]